MPImfp.cp311-win_amd64.pyd
MPImfp-0.0.1.dist-info/LICENSE
MPImfp-0.0.1.dist-info/METADATA
MPImfp-0.0.1.dist-info/WHEEL
MPImfp-0.0.1.dist-info/top_level.txt
MPImfp-0.0.1.dist-info/RECORD
