Metadata-Version: 2.1
Name: MPImfp
Version: 0.0.1
Summary: Python library to measure the image mean free path (IMFP)
Author-email: Kenjiro Sugio <ksugio@hiroshima-u.ac.jp>
License: MIT License
Project-URL: Homepage, https://github.com/ksugio/MPImfp
Classifier: Development Status :: 4 - Beta
Classifier: Programming Language :: Python
Classifier: Programming Language :: Python :: 3
Requires-Python: >=3.8
License-File: LICENSE
Requires-Dist: numpy
Provides-Extra: dev
Requires-Dist: build ; extra == 'dev'
Requires-Dist: twine ; extra == 'dev'
